simcardems/__init__.py
simcardems/__main__.py
simcardems/benchmark.py
simcardems/boundary_conditions.py
simcardems/cli.py
simcardems/config.py
simcardems/datacollector.py
simcardems/ep_model.py
simcardems/geometry.py
simcardems/gui.py
simcardems/lvgeometry.py
simcardems/mechanics_model.py
simcardems/newton_solver.py
simcardems/postprocess.py
simcardems/runner.py
simcardems/save_load_functions.py
simcardems/slabgeometry.py
simcardems/time_stepper.py
simcardems/utils.py
simcardems/value_extractor.py
simcardems/version.py
simcardems/models/__init__.py
simcardems/models/cell_model.py
simcardems/models/em_model.py
simcardems/models/explicit_ORdmm_Land/__init__.py
simcardems/models/explicit_ORdmm_Land/cell_model.py
simcardems/models/explicit_ORdmm_Land/em_model.py
simcardems/models/fully_coupled_ORdmm_Land/__init__.py
simcardems/models/fully_coupled_ORdmm_Land/active_model.py
simcardems/models/fully_coupled_ORdmm_Land/cell_model.py
simcardems/models/fully_coupled_ORdmm_Land/em_model.py
simcardems/models/fully_coupled_Tor_Land/__init__.py
simcardems/models/fully_coupled_Tor_Land/active_model.py
simcardems/models/fully_coupled_Tor_Land/cell_model.py
simcardems/models/fully_coupled_Tor_Land/em_model.py
simcardems/models/pureEP_ORdmm_Land/__init__.py
simcardems/models/pureEP_ORdmm_Land/cell_model.py
simcardems/models/pureEP_ORdmm_Land/em_model.py
simcardems-2023.7.1.dist-info/LICENSE
simcardems-2023.7.1.dist-info/METADATA
simcardems-2023.7.1.dist-info/WHEEL
simcardems-2023.7.1.dist-info/entry_points.txt
simcardems-2023.7.1.dist-info/top_level.txt
simcardems-2023.7.1.dist-info/RECORD
