Metadata-Version: 2.1
Name: simcardems
Version: 2023.7.1
Summary: Simula Cardiac electromechanics solver
Home-page: https://github.com/ComputationalPhysiology/simcardems
Author: Henrik Finsberg, Ilsbeth van Herck, Cécile Daversin-Catty
Author-email: henriknf@simula.no
License: LGPL-2.1
Keywords: action potential,cardiac mechanics,electrophysiology,electromechanics
Classifier: License :: OSI Approved :: GNU Lesser General Public License v2 (LGPLv2)
Classifier: Programming Language :: Python :: 3
Classifier: Programming Language :: Python :: 3 :: Only
Requires-Python: >=3.8
License-File: LICENSE
Requires-Dist: ap-features
Requires-Dist: cardiac-geometries
Requires-Dist: cbcbeat
Requires-Dist: click
Requires-Dist: fenics-pulse
Requires-Dist: h5py
Requires-Dist: matplotlib
Requires-Dist: numpy
Requires-Dist: scipy
Requires-Dist: tqdm
Requires-Dist: typing-extensions
Provides-Extra: dev
Requires-Dist: Sphinx ; extra == 'dev'
Requires-Dist: black ; extra == 'dev'
Requires-Dist: build ; extra == 'dev'
Requires-Dist: bump2version ; extra == 'dev'
Requires-Dist: flake8 ; extra == 'dev'
Requires-Dist: ipython ; extra == 'dev'
Requires-Dist: isort ; extra == 'dev'
Requires-Dist: mypy ; extra == 'dev'
Requires-Dist: pdbpp ; extra == 'dev'
Requires-Dist: pip ; extra == 'dev'
Requires-Dist: pre-commit ; extra == 'dev'
Requires-Dist: pytest ; extra == 'dev'
Requires-Dist: pytest-cov ; extra == 'dev'
Requires-Dist: sphinx ; extra == 'dev'
Requires-Dist: twine ; extra == 'dev'
Requires-Dist: wheel ; extra == 'dev'
Provides-Extra: docs
Requires-Dist: jupyter-book ; extra == 'docs'
Requires-Dist: jupytext ; extra == 'docs'
Requires-Dist: pandas ; extra == 'docs'
Requires-Dist: plotly ; extra == 'docs'
Requires-Dist: requests ; extra == 'docs'
Requires-Dist: sphinxcontrib-bibtex ; extra == 'docs'
Provides-Extra: gui
Requires-Dist: fenics-plotly ; extra == 'gui'
Requires-Dist: streamlit ; extra == 'gui'
